[{"id":"2a8a95ae1da827d9","type":"tab","label":"Temperatura outdoor","disabled":true,"info":"","env":[]},{"id":"37d5f1ec31525068","type":"poll-state","z":"2a8a95ae1da827d9","name":"Temperatura sensor","server":"1a815b35.439885","version":2,"exposeToHomeAssistant":false,"haConfig":[{"property":"name","value":""},{"property":"icon","value":""}],"updateinterval":"10","updateIntervalType":"num","updateIntervalUnits":"seconds","outputinitially":true,"outputonchanged":true,"entity_id":"sensor.outdoor_temperature","state_type":"str","halt_if":"0","halt_if_type":"num","halt_if_compare":"gt","outputs":2,"x":110,"y":100,"wires":[["52f9c9a32ffc33e3"],[]]},{"id":"c1519eeed38ad67e","type":"http request","z":"2a8a95ae1da827d9","name":"Enviar","method":"POST","ret":"txt","paytoqs":"ignore","url":"http://107.20.84.189/api/1234/1/{{{var_temp}}}","tls":"","persist":false,"proxy":"","insecureHTTPParser":false,"authType":"","senderr":false,"headers":[],"x":470,"y":100,"wires":[[]]},{"id":"52f9c9a32ffc33e3","type":"change","z":"2a8a95ae1da827d9","name":"","rules":[{"t":"set","p":"var_temp","pt":"msg","to":"payload","tot":"msg"}],"action":"","property":"","from":"","to":"","reg":false,"x":310,"y":100,"wires":[["c1519eeed38ad67e","3fc74ac66638ba46"]]},{"id":"3fc74ac66638ba46","type":"debug","z":"2a8a95ae1da827d9","name":"debug 6","active":true,"tosidebar":true,"console":false,"tostatus":false,"complete":"false","statusVal":"","statusType":"auto","x":500,"y":260,"wires":[]},{"id":"1a815b35.439885","type":"server","name":"Home Assistant","addon":true,"rejectUnauthorizedCerts":true,"ha_boolean":"","connectionDelay":false,"cacheJson":false,"heartbeat":false,"heartbeatInterval":"","statusSeparator":"","enableGlobalContextStore":false}]